Metadata-Version: 2.1
Name: Office-helper-functions
Version: 0.1.131
Summary: Helper functions for Microsoft Office
Author: Andreas Löfkvist
Author-email: andreasmlofkvist@gmail.com
License: MIT
